gdo_arch_utils/connections/__init__.py
gdo_arch_utils/connections/gcs_client_connection.py
gdo_arch_utils/connections/sapmc_connection.py
gdo_arch_utils/connections/sftp_connection.py
gdo_arch_utils/connections/snowflake_connection.py
gdo_arch_utils/decorators/__init__.py
gdo_arch_utils/decorators/timed_decorator.py
gdo_arch_utils/dto/__init__.py
gdo_arch_utils/dto/manifest.py
gdo_arch_utils/utils/__init__.py
gdo_arch_utils/utils/args_utils.py
gdo_arch_utils/utils/bool_utils.py
gdo_arch_utils/utils/date_utils.py
gdo_arch_utils/utils/dict_utils.py
gdo_arch_utils/utils/email_utils.py
gdo_arch_utils/utils/file_utils.py
gdo_arch_utils/utils/gcs_utils.py
gdo_arch_utils/utils/list_utils.py
gdo_arch_utils/utils/log_utils.py
gdo_arch_utils/utils/manifest_utils.py
gdo_arch_utils/utils/pandas_utils.py
gdo_arch_utils/utils/sftp_utils.py
gdo_arch_utils/utils/snowflake_utils.py
gdo_arch_utils/utils/string_utils.py
gdo_arch_utils/utils/template_utils.py
gdo_arch_utils/utils/traceback_utils.py
gdo_arch_utils/vars/__init__.py
gdo_arch_utils/vars/manifest_vars.py
gdo_arch_utils-0.0.10.dist-info/LICENSE.md
gdo_arch_utils-0.0.10.dist-info/METADATA
gdo_arch_utils-0.0.10.dist-info/WHEEL
gdo_arch_utils-0.0.10.dist-info/top_level.txt
gdo_arch_utils-0.0.10.dist-info/RECORD
